adafruit_tpa2016.py
adafruit_circuitpython_tpa2016-1.1.21.dist-info/licenses/LICENSE
adafruit_circuitpython_tpa2016-1.1.21.dist-info/METADATA
adafruit_circuitpython_tpa2016-1.1.21.dist-info/WHEEL
adafruit_circuitpython_tpa2016-1.1.21.dist-info/top_level.txt
adafruit_circuitpython_tpa2016-1.1.21.dist-info/RECORD
